{
  "scene_states": [
    {
      "idx": 1,
      "name": "locked_with_Sensorlock",
      "object_states": {
        "receptacle_state": "locked",
        "items": [
          "Sensorlock"
        ]
      },
      "image_path": "exitdoorL.png"
    },
    {
      "idx": 2,
      "name": "open",
      "object_states": {
        "receptacle_state": "open",
        "items": []
      },
      "image_path": "exitdoorO.png"
    },
    {
      "idx": 3,
      "name": "closed",
      "object_states": {
        "receptacle_state": "closed",
        "items": []
      },
      "image_path": "exitdoorC.png"
    }
  ]
}